LICENSE
MANIFEST.in
README.rst
setup.py
HangupsBot.egg-info/PKG-INFO
HangupsBot.egg-info/SOURCES.txt
HangupsBot.egg-info/dependency_links.txt
HangupsBot.egg-info/entry_points.txt
HangupsBot.egg-info/requires.txt
HangupsBot.egg-info/top_level.txt
hangupsbot/__init__.py
hangupsbot/__main__.py
hangupsbot/config.json
hangupsbot/config.py
hangupsbot/utils.py
hangupsbot/version.py
hangupsbot/commands/__init__.py
hangupsbot/commands/config.py
hangupsbot/commands/conversations.py
hangupsbot/commands/default.py
hangupsbot/commands/jokes.py
hangupsbot/commands/users.py
hangupsbot/handlers/__init__.py
hangupsbot/handlers/autoreplies.py
hangupsbot/handlers/commands.py
hangupsbot/handlers/forwarding.py
hangupsbot/handlers/membership.py
hangupsbot/handlers/rename.py
hangupsbot/locale/cs/LC_MESSAGES/hangupsbot.mo
hangupsbot/locale/cs/LC_MESSAGES/hangupsbot.po